wagtail_cache_block/__init__.py
wagtail_cache_block/apps.py
wagtail_cache_block/templatetags/__init__.py
wagtail_cache_block/templatetags/cache_block_tags.py
wagtail_cache_block-0.1.3.dist-info/DESCRIPTION.rst
wagtail_cache_block-0.1.3.dist-info/METADATA
wagtail_cache_block-0.1.3.dist-info/RECORD
wagtail_cache_block-0.1.3.dist-info/WHEEL
wagtail_cache_block-0.1.3.dist-info/metadata.json
wagtail_cache_block-0.1.3.dist-info/top_level.txt
