Metadata-Version: 2.0
Name: wagtail-cache-block
Version: 0.1.3
Summary: Easily make your Wagtail StreamBlock cacheable
Home-page: https://github.com/Accordbox/wagtail_cache_block
Author: michaelyin
Author-email: michaelyin@accordbox.com
License: BSD
Keywords: wagtail_cache_block
Platform: UNKNOWN
Classifier: Development Status :: 3 - Alpha
Classifier: Framework :: Django :: 1.11
Classifier: Framework :: Django :: 2.1
Classifier: Intended Audience :: Developers
Classifier: License :: OSI Approved :: BSD License
Classifier: Natural Language :: English
Classifier: Programming Language :: Python :: 2
Classifier: Programming Language :: Python :: 2.7
Classifier: Programming Language :: Python :: 3
Classifier: Programming Language :: Python :: 3.5
Classifier: Programming Language :: Python :: 3.6
Requires-Dist: wagtail (>=2)
Requires-Dist: Django (<3,>=2)
